LICENSE
README.md
setup.cfg
setup.py
functions/__init__.py
functions/gp_functions.py
functions/gp_optimization.py
functions/gp_regression.py
gp_approx.egg-info/PKG-INFO
gp_approx.egg-info/SOURCES.txt
gp_approx.egg-info/dependency_links.txt
gp_approx.egg-info/requires.txt
gp_approx.egg-info/top_level.txt